best_book_store/__init__.py
best_book_store-0.0.2.dist-info/LICENSE
best_book_store-0.0.2.dist-info/METADATA
best_book_store-0.0.2.dist-info/WHEEL
best_book_store-0.0.2.dist-info/top_level.txt
best_book_store-0.0.2.dist-info/RECORD
