Metadata-Version: 1.0
Name: best-book-store
Version: 0.0.2
Summary: The best book store management system
Home-page: https://github.com/radcheb/book-store
Author: radcheb
Author-email: radcheb@example.com
License: MIT
Platform: UNKNOWN
